dbt_metricflow/__about__.py
dbt_metricflow/__init__.py
dbt_metricflow/py.typed
dbt_metricflow/cli/__init__.py
dbt_metricflow/cli/cli_configuration.py
dbt_metricflow/cli/cli_errors.py
dbt_metricflow/cli/cli_link.py
dbt_metricflow/cli/cli_string.py
dbt_metricflow/cli/constants.py
dbt_metricflow/cli/custom_click_types.py
dbt_metricflow/cli/main.py
dbt_metricflow/cli/tutorial.py
dbt_metricflow/cli/utils.py
dbt_metricflow/cli/dbt_connectors/__init__.py
dbt_metricflow/cli/dbt_connectors/adapter_backed_client.py
dbt_metricflow/cli/dbt_connectors/dbt_config_accessor.py
dbt_metricflow/cli/mf_tutorial_project/dbt_project.yml
dbt_metricflow/cli/mf_tutorial_project/profiles.yml
dbt_metricflow/cli/mf_tutorial_project/models/_models.yml
dbt_metricflow/cli/mf_tutorial_project/models/all_days.sql
dbt_metricflow/cli/sample_dbt_models/sources.yml
dbt_metricflow/cli/sample_dbt_models/sample_models/countries.sql
dbt_metricflow/cli/sample_dbt_models/sample_models/countries.yml
dbt_metricflow/cli/sample_dbt_models/sample_models/customers.sql
dbt_metricflow/cli/sample_dbt_models/sample_models/customers.yml
dbt_metricflow/cli/sample_dbt_models/sample_models/metrics.yml
dbt_metricflow/cli/sample_dbt_models/sample_models/saved_queries.yml
dbt_metricflow/cli/sample_dbt_models/sample_models/transactions.sql
dbt_metricflow/cli/sample_dbt_models/sample_models/transactions.yml
dbt_metricflow/cli/sample_dbt_models/seeds/.gitkeep
dbt_metricflow/cli/sample_dbt_models/seeds/countries_seed.csv
dbt_metricflow/cli/sample_dbt_models/seeds/customers_seed.csv
dbt_metricflow/cli/sample_dbt_models/seeds/transactions_seed.csv
dbt_metricflow/cli/sample_models/project_configuration.yaml
dbt_metricflow-0.11.0.dist-info/METADATA
dbt_metricflow-0.11.0.dist-info/WHEEL
dbt_metricflow-0.11.0.dist-info/entry_points.txt
dbt_metricflow-0.11.0.dist-info/licenses/LICENSE
dbt_metricflow-0.11.0.dist-info/RECORD
