Metadata-Version: 2.4
Name: dbt-metricflow
Version: 0.11.0
Summary: Execute commands against the MetricFlow semantic layer with dbt.
Project-URL: Source Code, https://github.com/dbt-labs/metricflow/tree/main/dbt-metricflow
Author-email: dbt Labs <info@dbtlabs.com>
License-Expression: Apache-2.0
License-File: LICENSE
Classifier: Development Status :: 4 - Beta
Classifier: Programming Language :: Python
Classifier: Programming Language :: Python :: 3.9
Classifier: Programming Language :: Python :: 3.10
Classifier: Programming Language :: Python :: 3.11
Classifier: Programming Language :: Python :: 3.12
Classifier: Programming Language :: Python :: Implementation :: CPython
Classifier: Programming Language :: Python :: Implementation :: PyPy
Requires-Python: <3.13,>=3.9
Requires-Dist: click>=8.1.6
Requires-Dist: dbt-core<1.11.0,>=1.10.4
Requires-Dist: dbt-semantic-interfaces
Requires-Dist: halo<0.1.0,>=0.0.31
Requires-Dist: jinja2<3.7.0,>=3.1.6
Requires-Dist: metricflow==0.209.0
Requires-Dist: update-checker<0.19.0,>=0.18.0
Provides-Extra: dbt-bigquery
Requires-Dist: dbt-bigquery; extra == 'dbt-bigquery'
Provides-Extra: dbt-databricks
Requires-Dist: dbt-databricks; extra == 'dbt-databricks'
Provides-Extra: dbt-duckdb
Requires-Dist: dbt-duckdb; extra == 'dbt-duckdb'
Provides-Extra: dbt-postgres
Requires-Dist: dbt-postgres; extra == 'dbt-postgres'
Provides-Extra: dbt-redshift
Requires-Dist: dbt-redshift; extra == 'dbt-redshift'
Provides-Extra: dbt-snowflake
Requires-Dist: dbt-snowflake; extra == 'dbt-snowflake'
Provides-Extra: dbt-trino
Requires-Dist: dbt-trino; extra == 'dbt-trino'
